bqapi-0.5.9.dist-info/top_level.txt
bqapi-0.5.9.dist-info/WHEEL
bqapi-0.5.9.dist-info/DESCRIPTION.rst
bqapi-0.5.9.dist-info/RECORD
bqapi-0.5.9.dist-info/METADATA
bqapi-0.5.9.dist-info/metadata.json
bqapi-0.5.9.dist-info/zip-safe
tests/test_comm.py
tests/test_util.py
tests/test_bqapi.py
tests/test_bqfeature.py
tests/conftest.py
tests/util.py
tests/__init__.py
tests/test_bqclass.py
bqapi/xmldict.py
bqapi/types.py
bqapi/bqfeature.py
bqapi/bqclass.py
bqapi/util.py
bqapi/bqnode.py
bqapi/__init__.py
bqapi/casauth.py
bqapi/comm.py
bqapi/RequestsMonkeyPatch/requests_patch.py
bqapi/RequestsMonkeyPatch/monkeypatch.py
bqapi/RequestsMonkeyPatch/__init__.py
