Metadata-Version: 2.0
Name: bqapi
Version: 0.5.9
Summary: Bisque Module API
Home-page: http://biodeve.ece.ucsb.edu/projects/bisquik
Author: Center for Bioimage informatics
Author-email: cbi@biodev.ece.ucsb.edu
License: UNKNOWN
Platform: UNKNOWN
Requires-Dist: requests (>=2.4.1)
Requires-Dist: requests-toolbelt (>=0.6.2)
Provides-Extra: CAS
Requires-Dist: BeautifulSoup4; extra == 'CAS'
Provides-Extra: bqfeature
Requires-Dist: tables; extra == 'bqfeature'
Provides-Extra: lxml
Requires-Dist: lxml; extra == 'lxml'
